{
  "currentcoursedata": [
    {
      "id": 0,
      "name": "Philosophy",
      "currentWarmUpURL": "https://classroom.google.com/c/NjQ2ODIxNDE4NjEy/a/NjU5NzcyNDc4NjE2/details",
      "currentGoogleClassroomPage": "https://classroom.google.com/w/NjQ2ODIxNDE4NjEy/t/all",
      "currentExtra": "https://classroom.google.com/c/NjQ2ODIxNDE4NjEy/a/NjQ2ODIxNDE4NjM4/details"
    },
    {
      "id": 2,
      "name": "Personal Finance",
      "currentWarmUpURL": "https://classroom.google.com/c/NjUzMjgzMDI5MjYx/a/NjY2MzYzNzM4OTQy/details",
      "currentGoogleClassroomPage": "https://classroom.google.com/w/NjUzMjgzMDI5MjYx/t/all",
      "currentExtra": "https://classroom.google.com/c/NjUzMjgzMDI5MjYx/a/NjQ3MDQzNTc1MzAx/details"
    },
    {
      "id": 13,
      "name": "The History of Disease",
      "currentWarmUpURL": "https://classroom.google.com/c/NjQ2ODUxNDYzMDg4/a/NjQ4OTM0MjEyNzMz/details",
      "currentGoogleClassroomPage": "https://classroom.google.com/w/NjQ2ODUxNDYzMDg4/t/all",
      "currentExtra": "https://classroom.google.com/c/NjQ2ODUxNDYzMDg4/a/NjQ3MDQxNTIzNDk4/details"
    },
    {
      "id": 18,
      "name": "Native America",
      "currentWarmUpURL": "https://classroom.google.com/c/NjQ2ODUxNTQ2NjY5/a/NjU4OTQzNzgzNzUy/details",
      "currentGoogleClassroomPage": "https://classroom.google.com/w/NjQ2ODUxNTQ2NjY5/t/all",
      "currentExtra": "https://classroom.google.com/c/NjQ2ODUxNTQ2NjY5/a/NjQ2ODUxNTQ2NzIz/details"
    },
    {
      "id": 10,
      "name": "Government",
      "currentWarmUpURL": "https://classroom.google.com/c/NjUzMjgzMDI5MjYx/a/NjY2MzYzNzM4OTQy/details",
      "currentGoogleClassroomPage": "https://classroom.google.com/w/NjUzMjgxOTc0MjEz/t/all",
      "currentExtra": "https://classroom.google.com/c/NjUzMjgxOTc0MjEz/a/NjUzMjgxOTc0Mjg2/details"
    }
  ]
}
